<?xml version = '1.0'  encoding = 'ISO-8859-1'  standalone = 'yes' ?>
<!-- PlotDigitizer data file: created on Sat Nov 04 19:31:18 EDT 2017 -->
<data>
<image file='AMADO0513_TTP.png' />
<axesnames x='months'  y='p' />
<calibpoints minXaxisX='89.0' minXaxisY='343.0' maxXaxisX='557.0' maxXaxisY='343.0' minYaxisX='65.0' minYaxisY='317.0' maxYaxisX='64.0' maxYaxisY='86.0' aX1='0.0' aX2='24.0' aY1='0.0' aY2='1.0' isXLog='false' isYLog='false' />
<point n='0' x='88.66666666666667' y='85.33333333333333' dx='-0.017094017094017033' dy='1.002886002886003' />
<point n='1' x='104.66666666666667' y='85.33333333333333' dx='0.8034188034188041' dy='1.002886002886003' />
<point n='2' x='104.0' y='89.33333333333333' dx='0.7692307692307692' dy='0.9855699855699857' />
<point n='3' x='112.66666666666667' y='88.0' dx='1.2136752136752138' dy='0.9913419913419914' />
<point n='4' x='112.66666666666667' y='96.0' dx='1.2136752136752138' dy='0.9567099567099567' />
<point n='5' x='118.0' y='97.33333333333333' dx='1.4871794871794872' dy='0.950937950937951' />
<point n='6' x='119.33333333333333' y='106.66666666666667' dx='1.5555555555555554' dy='0.9105339105339105' />
<point n='7' x='124.0' y='109.33333333333333' dx='1.7948717948717947' dy='0.898989898989899' />
<point n='8' x='125.33333333333333' y='120.66666666666667' dx='1.8632478632478628' dy='0.84992784992785' />
<point n='9' x='127.0' y='120.66666666666667' dx='1.948717948717949' dy='0.84992784992785' />
<point n='10' x='127.0' y='125.0' dx='1.948717948717949' dy='0.8311688311688312' />
<point n='11' x='132.66666666666666' y='124.66666666666667' dx='2.2393162393162385' dy='0.8326118326118327' />
<point n='12' x='136.0' y='135.33333333333334' dx='2.4102564102564106' dy='0.7864357864357865' />
<point n='13' x='140.33333333333334' y='135.66666666666666' dx='2.632478632478633' dy='0.7849927849927851' />
<point n='14' x='140.66666666666666' y='140.0' dx='2.649572649572649' dy='0.7662337662337663' />
<point n='15' x='142.33333333333334' y='147.0' dx='2.735042735042735' dy='0.735930735930736' />
<point n='16' x='146.66666666666666' y='146.66666666666666' dx='2.9572649572649565' dy='0.7373737373737375' />
<point n='17' x='146.33333333333334' y='151.33333333333334' dx='2.9401709401709404' dy='0.7171717171717171' />
<point n='18' x='151.33333333333334' y='150.66666666666666' dx='3.1965811965811968' dy='0.7200577200577202' />
<point n='19' x='154.33333333333334' y='157.33333333333334' dx='3.350427350427351' dy='0.6911976911976913' />
<point n='20' x='161.66666666666666' y='157.66666666666666' dx='3.7264957264957257' dy='0.6897546897546899' />
<point n='21' x='161.66666666666666' y='165.33333333333334' dx='3.7264957264957257' dy='0.6565656565656566' />
<point n='22' x='164.33333333333334' y='165.33333333333334' dx='3.8632478632478637' dy='0.6565656565656566' />
<point n='23' x='164.33333333333334' y='169.33333333333334' dx='3.8632478632478637' dy='0.6392496392496393' />
<point n='24' x='169.0' y='170.33333333333334' dx='4.102564102564102' dy='0.6349206349206349' />
<point n='25' x='180.0' y='184.33333333333334' dx='4.666666666666666' dy='0.5743145743145743' />
<point n='26' x='180.66666666666666' y='190.66666666666666' dx='4.7008547008547' dy='0.546897546897547' />
<point n='27' x='183.0' y='191.33333333333334' dx='4.820512820512821' dy='0.5440115440115441' />
<point n='28' x='183.0' y='199.33333333333334' dx='4.820512820512821' dy='0.5093795093795094' />
<point n='29' x='188.0' y='198.66666666666666' dx='5.076923076923077' dy='0.5122655122655123' />
<point n='30' x='188.0' y='202.0' dx='5.076923076923077' dy='0.49783549783549785' />
<point n='31' x='193.33333333333334' y='203.0' dx='5.350427350427351' dy='0.49350649350649356' />
<point n='32' x='194.0' y='208.0' dx='5.384615384615385' dy='0.47186147186147187' />
<point n='33' x='220.66666666666666' y='206.33333333333334' dx='6.752136752136751' dy='0.4790764790764791' />
<point n='34' x='220.33333333333334' y='210.66666666666666' dx='6.735042735042736' dy='0.46031746031746046' />
<point n='35' x='229.0' y='210.66666666666666' dx='7.179487179487179' dy='0.46031746031746046' />
<point n='36' x='229.0' y='214.66666666666666' dx='7.179487179487179' dy='0.44300144300144306' />
<point n='37' x='238.33333333333334' y='214.66666666666666' dx='7.658119658119658' dy='0.44300144300144306' />
<point n='38' x='238.66666666666666' y='220.66666666666666' dx='7.675213675213675' dy='0.4170274170274171' />
<point n='39' x='245.0' y='225.0' dx='8.0' dy='0.3982683982683983' />
<point n='40' x='246.33333333333334' y='231.33333333333334' dx='8.068376068376068' dy='0.37085137085137077' />
<point n='41' x='250.66666666666666' y='231.0' dx='8.29059829059829' dy='0.37229437229437234' />
<point n='42' x='251.0' y='235.33333333333334' dx='8.307692307692307' dy='0.3535353535353536' />
<point n='43' x='262.3333333333333' y='236.33333333333334' dx='8.888888888888888' dy='0.3492063492063493' />
<point n='44' x='261.6666666666667' y='242.0' dx='8.854700854700855' dy='0.3246753246753247' />
<point n='45' x='275.0' y='241.33333333333334' dx='9.538461538461538' dy='0.3275613275613276' />
<point n='46' x='275.3333333333333' y='246.0' dx='9.555555555555554' dy='0.3073593073593075' />
<point n='47' x='279.6666666666667' y='246.66666666666666' dx='9.777777777777779' dy='0.30447330447330456' />
<point n='48' x='279.6666666666667' y='252.0' dx='9.777777777777779' dy='0.2813852813852815' />
<point n='49' x='299.3333333333333' y='251.66666666666666' dx='10.786324786324785' dy='0.2828282828282829' />
<point n='50' x='299.3333333333333' y='258.0' dx='10.786324786324785' dy='0.25541125541125553' />
<point n='51' x='335.6666666666667' y='258.0' dx='12.649572649572649' dy='0.25541125541125553' />
<point n='52' x='336.0' y='263.6666666666667' dx='12.666666666666666' dy='0.2308802308802309' />
<point n='53' x='353.6666666666667' y='265.3333333333333' dx='13.572649572649572' dy='0.2236652236652239' />
<point n='54' x='353.3333333333333' y='271.6666666666667' dx='13.555555555555555' dy='0.19624819624819612' />
<point n='55' x='391.3333333333333' y='272.6666666666667' dx='15.504273504273504' dy='0.19191919191919182' />
<point n='56' x='391.3333333333333' y='286.0' dx='15.504273504273504' dy='0.1341991341991342' />
<point n='57' x='423.6666666666667' y='286.6666666666667' dx='17.162393162393165' dy='0.13131313131313127' />
<point n='58' x='423.6666666666667' y='296.3333333333333' dx='17.162393162393165' dy='0.0894660894660897' />
<point n='59' x='434.3333333333333' y='296.3333333333333' dx='17.70940170940171' dy='0.0894660894660897' />
</data>
