<?xml version = '1.0'  encoding = 'ISO-8859-1'  standalone = 'yes' ?>
<!-- PlotDigitizer data file: created on Fri Mar 08 14:41:50 IST 2019 -->
<data>
<image file='ANDER0111_TTP.PNG' />
<axesnames x='Months'  y='p' />
<calibpoints minXaxisX='116.0' minXaxisY='322.0' maxXaxisX='514.0' maxXaxisY='323.0' minYaxisX='116.0' minYaxisY='322.0' maxYaxisX='117.0' maxYaxisY='23.0' aX1='0.0' aX2='60.0' aY1='0.0' aY2='1.0' isXLog='false' isYLog='false' />
<point n='0' x='118.0' y='23.0' dx='0.18825163347116458' dy='1.0000084031495005' />
<point n='1' x='135.0' y='28.0' dx='2.7529434045642454' dy='0.9834289891851465' />
<point n='2' x='143.0' y='40.0' dx='3.963511252801357' dy='0.9433627723670832' />
<point n='3' x='151.0' y='52.0' dx='5.174079101038476' dy='0.9032965555490198' />
<point n='4' x='157.0' y='62.0' dx='6.082383763138786' dy='0.8699024394343' />
<point n='5' x='183.0' y='105.0' dx='10.018244373599316' dy='0.7263094207709049' />
<point n='6' x='161.0' y='77.0' dx='6.691076670559635' dy='0.8197692495147181' />
<point n='7' x='173.0' y='90.0' dx='8.505034563302917' dy='0.7763921917934842' />
<point n='8' x='195.0' y='143.0' dx='11.841671664404526' dy='0.5993210255203651' />
<point n='9' x='214.0' y='171.0' dx='14.716580916006432' dy='0.5058359873280506' />
<point n='10' x='227.0' y='189.0' dx='16.683185505508025' dy='0.4457450652504559' />
<point n='11' x='239.0' y='196.0' dx='18.494870742716447' dy='0.4224347285362554' />
<point n='12' x='258.0' y='206.0' dx='21.362962027713767' dy='0.38914985336504127' />
<point n='13' x='287.0' y='231.0' dx='25.744263123007467' dy='0.3057822071712478' />
<point n='14' x='311.0' y='235.0' dx='29.36384583819954' dy='0.2926060687545693' />
<point n='15' x='332.0' y='245.0' dx='32.5334427574887' dy='0.25933799988235595' />
<point n='16' x='343.0' y='256.0' dx='34.19589028124112' dy='0.22264144601396607' />
<point n='17' x='358.0' y='256.0' dx='36.45718253842996' dy='0.2227674932564726' />
<point n='18' x='395.0' y='264.0' dx='42.03806698020895' dy='0.19632278177861073' />
<point n='19' x='413.0' y='275.0' dx='44.755784223982815' dy='0.15968504995672372' />
<point n='20' x='429.0' y='276.0' dx='47.168208074240056' dy='0.15647504684755842' />
<point n='21' x='428.0' y='286.0' dx='47.021243016318905' dy='0.12302210868633567' />
</data>
