<?xml version = '1.0'  encoding = 'ISO-8859-1'  standalone = 'yes' ?>
<!-- PlotDigitizer data file: created on Thu Aug 16 13:43:13 EDT 2018 -->
<data>
<image file='BASEL0512_PFS.png' />
<axesnames x='months'  y='p' />
<calibpoints minXaxisX='296.0' minXaxisY='649.0' maxXaxisX='1272.5' maxXaxisY='650.0' minYaxisX='296.0' minYaxisY='649.0' maxYaxisX='296.5' maxYaxisY='202.0' aX1='0.0' aX2='15.0' aY1='0.0' aY2='1.0' isXLog='false' isYLog='false' />
<point n='0' x='298.0' y='201.5' dx='0.023682473946787574' dy='1.001122003408966' />
<point n='1' x='309.0' y='202.0' dx='0.1926609761961382' dy='1.0000286371467322' />
<point n='2' x='321.5' y='202.0' dx='0.384673063617579' dy='1.0000572742934644' />
<point n='3' x='328.5' y='201.0' dx='0.4921841019366253' dy='1.0023104449983506' />
<point n='4' x='332.5' y='213.0' dx='0.5538167375550342' dy='0.9754740020527108' />
<point n='5' x='379.0' y='219.0' dx='1.268196086584572' dy='0.9621577288222574' />
<point n='6' x='383.0' y='231.5' dx='1.329836587521462' dy='0.9342027189252594' />
<point n='7' x='397.0' y='252.5' dx='1.5452204688096858' dy='0.8872549805725598' />
<point n='8' x='431.5' y='263.0' dx='2.0753390017809705' dy='0.8638441131190208' />
<point n='9' x='452.5' y='263.5' dx='2.3979271739674735' dy='0.8627736565741727' />
<point n='10' x='464.5' y='266.5' dx='2.5823059698029454' dy='0.856089746526887' />
<point n='11' x='477.0' y='288.0' dx='2.7746562659190763' dy='0.8080200047652214' />
<point n='12' x='488.0' y='301.5' dx='2.9438392664489372' dy='0.7778438977676774' />
<point n='13' x='499.0' y='315.5' dx='3.1130301322972773' dy='0.7465492238187751' />
<point n='14' x='535.5' y='323.0' dx='3.6738234073451057' dy='0.7298543400168618' />
<point n='15' x='558.5' y='323.0' dx='4.027125648200558' dy='0.729907032366849' />
<point n='16' x='563.5' y='340.5' dx='4.104205769315975' dy='0.6907686439280087' />
<point n='17' x='573.0' y='363.0' dx='4.250488895087923' dy='0.6404548953484113' />
<point n='18' x='596.0' y='378.0' dx='4.604027095497811' dy='0.6069505791576558' />
<point n='19' x='652.0' y='389.5' dx='5.464422149470938' dy='0.5813518336937797' />
<point n='20' x='688.0' y='417.0' dx='6.017849553761156' dy='0.5199131263516736' />
<point n='21' x='715.5' y='430.0' dx='6.4404806443688365' dy='0.490893387339174' />
<point n='22' x='751.5' y='436.5' dx='6.993577705282846' dy='0.4764344919541076' />
<point n='23' x='790.0' y='445.0' dx='7.585108644955065' dy='0.45750705619295495' />
<point n='24' x='813.5' y='479.0' dx='7.946626210964094' dy='0.38149834133646165' />
<point n='25' x='845.0' y='483.5' dx='8.430567459132458' dy='0.37150340438400375' />
<point n='26' x='899.5' y='490.0' dx='9.267842409430202' dy='0.3570868919761008' />
<point n='27' x='913.0' y='506.0' dx='9.475467154036755' dy='0.3213236776511126' />
<point n='28' x='932.0' y='515.0' dx='9.767467102650008' dy='0.30123300098969996' />
<point n='29' x='938.0' y='534.5' dx='9.859939652033065' dy='0.2576226357171658' />
<point n='30' x='962.5' y='539.5' dx='10.236361996563904' dy='0.2464930950111801' />
<point n='31' x='973.0' y='565.0' dx='10.398053281240454' dy='0.18947023569517252' />
<point n='32' x='1059.5' y='563.0' dx='11.726745464922907' dy='0.19414267255599138' />
<point n='33' x='1067.0' y='602.0' dx='11.842566212217307' dy='0.10691163263809988' />
<point n='34' x='1204.0' y='607.5' dx='13.9471052088596' dy='0.09492125930134532' />
</data>
