<?xml version = '1.0'  encoding = 'ISO-8859-1'  standalone = 'yes' ?>
<!-- PlotDigitizer data file: created on Sun Nov 05 01:36:33 EDT 2017 -->
<data>
<image file='BONNE1102_OS.png' />
<axesnames x='months'  y='p' />
<calibpoints minXaxisX='60.5' minXaxisY='266.5' maxXaxisX='386.5' maxXaxisY='266.0' minYaxisX='58.5' minYaxisY='261.5' maxYaxisX='57.0' maxYaxisY='46.0' aX1='0.0' aX2='42.0' aY1='0.0' aY2='1.0' isXLog='false' isYLog='false' />
<point n='0' x='75.0' y='51.5' dx='1.9105773867632667' dy='0.9743501236588793' />
<point n='1' x='77.5' y='54.5' dx='2.2320697239505503' dy='0.9604113659413197' />
<point n='2' x='82.5' y='60.5' dx='2.8750543983251173' dy='0.9325338505062006' />
<point n='3' x='93.5' y='64.5' dx='4.291438585761162' dy='0.9138942761062575' />
<point n='4' x='97.0' y='65.0' dx='4.7422589713129675' dy='0.911549205558422' />
<point n='5' x='109.0' y='78.5' dx='6.285600028228318' dy='0.8488194580360477' />
<point n='6' x='112.0' y='89.0' dx='6.670027404994057' dy='0.800074729106987' />
<point n='7' x='114.5' y='90.0' dx='6.991914938662212' dy='0.7954166147714532' />
<point n='8' x='132.0' y='110.0' dx='9.24255889721363' dy='0.7024856324395493' />
<point n='9' x='134.0' y='114.5' dx='9.499337810658542' dy='0.6815899507143746' />
<point n='10' x='141.0' y='128.5' dx='10.3984098046365' dy='0.6165756276355354' />
<point n='11' x='154.5' y='134.5' dx='12.136483927500265' dy='0.5886376172090457' />
<point n='12' x='174.0' y='154.0' dx='14.644894790698771' dy='0.49801256160703145' />
<point n='13' x='184.5' y='154.0' dx='15.997652344714837' dy='0.4979378325000444' />
<point n='14' x='199.0' y='162.5' dx='17.864066524740945' dy='0.4583919007882141' />
<point n='15' x='206.5' y='162.5' dx='18.830321920466705' dy='0.45833852285465193' />
<point n='16' x='240.0' y='203.0' dx='23.138259959304172' dy='0.2701670729320498' />
<point n='17' x='298.0' y='230.5' dx='30.605201067971436' dy='0.14214543707631266' />
</data>
