<?xml version = '1.0'  encoding = 'ISO-8859-1'  standalone = 'yes' ?>
<!-- PlotDigitizer data file: created on Sat Sep 22 19:08:09 EDT 2018 -->
<data>
<image file='DESHM1107_PFS.png' />
<axesnames x='months'  y='p' />
<calibpoints minXaxisX='141.33333333333334' minXaxisY='506.3333333333333' maxXaxisX='849.6666666666666' maxXaxisY='510.3333333333333' minYaxisX='141.33333333333334' minYaxisY='506.3333333333333' maxYaxisX='141.0' maxYaxisY='49.0' aX1='0.0' aX2='20.0' aY1='0.0' aY2='1.0' isXLog='false' isYLog='false' />
<point n='0' x='147.66666666666666' y='49.333333333333336' dx='0.10595316102307173' dy='0.9993534530068381' />
<point n='1' x='158.33333333333334' y='50.333333333333336' dx='0.40727946890108857' dy='0.9972985654545655' />
<point n='2' x='175.0' y='51.333333333333336' dx='0.8780121392391846' dy='0.9953177649847985' />
<point n='3' x='180.66666666666666' y='65.0' dx='1.0401860679764603' dy='0.9655042311956009' />
<point n='4' x='181.0' y='75.33333333333333' dx='1.0512450924748356' dy='0.9429135019591919' />
<point n='5' x='203.0' y='78.33333333333333' dx='1.6728800786754139' dy='0.9366253608315316' />
<point n='6' x='208.0' y='96.33333333333333' dx='1.8169219904738245' dy='0.8973283374858687' />
<point n='7' x='215.0' y='122.33333333333333' dx='2.0187082200174533' dy='0.8405632264650036' />
<point n='8' x='223.0' y='131.0' dx='2.245965194410962' dy='0.8217114939248593' />
<point n='9' x='238.66666666666666' y='136.33333333333334' dx='2.689154383229078' dy='0.8102430879495988' />
<point n='10' x='249.33333333333334' y='149.33333333333334' dx='2.9923939864948794' dy='0.7819490253432702' />
<point n='11' x='253.0' y='162.66666666666666' dx='3.0980459806513565' dy='0.7528396618336279' />
<point n='12' x='263.0' y='171.33333333333334' dx='3.3817717425315594' dy='0.7340126249876522' />
<point n='13' x='277.6666666666667' y='182.33333333333334' dx='3.7976300382061163' dy='0.7101411496120033' />
<point n='14' x='283.6666666666667' y='203.66666666666666' dx='3.9704378146889265' dy='0.6635678143761868' />
<point n='15' x='290.3333333333333' y='215.66666666666666' dx='4.160580401699024' dy='0.6374109583026925' />
<point n='16' x='306.6666666666667' y='230.33333333333334' dx='4.624080638314316' dy='0.6055425369612223' />
<point n='17' x='326.3333333333333' y='232.33333333333334' dx='5.179675931164768' dy='0.6014121821115368' />
<point n='18' x='348.0' y='235.33333333333334' dx='5.7918994527842305' dy='0.5951199250348483' />
<point n='19' x='355.3333333333333' y='262.0' dx='6.003203441097185' dy='0.5369011980155638' />
<point n='20' x='379.6666666666667' y='269.0' dx='6.691356444494835' dy='0.5218954768464148' />
<point n='21' x='402.0' y='276.0' dx='7.323040660405789' dy='0.5068650599830972' />
<point n='22' x='422.6666666666667' y='291.0' dx='7.908943083669691' dy='0.4743212800052684' />
<point n='23' x='454.3333333333333' y='318.3333333333333' dx='8.807390280592296' dy='0.4149452853175867' />
<point n='24' x='472.0' y='332.0' dx='9.308376934249734' dy='0.3852799256934002' />
<point n='25' x='502.0' y='341.6666666666667' dx='10.156950012279191' dy='0.3645132478679384' />
<point n='26' x='508.6666666666667' y='356.6666666666667' dx='10.347570923136235' dy='0.33179659803092987' />
<point n='27' x='558.6666666666666' y='357.6666666666667' dx='11.759450051585898' dy='0.3302273924639717' />
<point n='28' x='573.6666666666666' y='379.3333333333333' dx='12.186420518852934' dy='0.28303632187818983' />
<point n='29' x='584.0' y='391.6666666666667' dx='12.480142363349408' dy='0.25619587527028065' />
<point n='30' x='587.6666666666666' y='411.0' dx='12.58675100519978' dy='0.2139669242336103' />
<point n='31' x='746.0' y='417.0' dx='17.058153328923602' dy='0.2028024124949236' />
<point n='32' x='747.3333333333334' y='446.3333333333333' dx='17.100476131529316' dy='0.13867867060334327' />
<point n='33' x='774.3333333333334' y='450.0' dx='17.863389380634842' dy='0.1309945367636567' />
<point n='34' x='774.6666666666666' y='476.3333333333333' dx='17.876999465650254' dy='0.073418240788506' />
</data>
