<?xml version = '1.0'  encoding = 'ISO-8859-1'  standalone = 'yes' ?>
<!-- PlotDigitizer data file: created on Sat Mar 16 06:41:21 IST 2019 -->
<data>
<image file='FALKS0796_TTF.PNG' />
<axesnames x='MONTHS'  y='P' />
<calibpoints minXaxisX='66.0' minXaxisY='353.0' maxXaxisX='548.0' maxXaxisY='354.0' minYaxisX='66.0' minYaxisY='353.0' maxYaxisX='68.0' maxYaxisY='26.0' aX1='0.0' aX2='40.0' aY1='0.0' aY2='1.0' isXLog='false' isYLog='false' />
<point n='0' x='73.0' y='28.0' dx='0.524954266652319' dy='0.9939155923256524' />
<point n='1' x='75.0' y='37.0' dx='0.6924782094049293' dy='0.9664056948533145' />
<point n='2' x='78.0' y='41.0' dx='0.942128483805015' dy='0.9541924677697697' />
<point n='3' x='79.0' y='45.0' dx='1.0258043688798022' dy='0.9419665516191251' />
<point n='4' x='79.0' y='48.0' dx='1.0263208866889064' dy='0.9327923561059792' />
<point n='5' x='83.0' y='60.0' dx='1.3603357365759168' dy='0.8961209521875952' />
<point n='6' x='85.0' y='68.0' dx='1.527687506725493' dy='0.871669119886306' />
<point n='7' x='89.0' y='72.0' dx='1.8603249757882274' dy='0.8594622373363112' />
<point n='8' x='90.0' y='81.0' dx='1.944861723878188' dy='0.8319459953304235' />
<point n='9' x='92.0' y='84.0' dx='2.111352631012589' dy='0.8227844888843774' />
<point n='10' x='92.0' y='95.0' dx='2.113246529645969' dy='0.7891457720028425' />
<point n='11' x='128.0' y='195.0' dx='5.118002797804798' dy='0.4835676581057762' />
<point n='12' x='95.0' y='104.0' dx='2.363757667061229' dy='0.7616422190640546' />
<point n='13' x='95.0' y='110.0' dx='2.3647907026794357' dy='0.7432938280377628' />
<point n='14' x='96.0' y='113.0' dx='2.4482944151511887' dy='0.7341259770581667' />
<point n='15' x='96.0' y='113.0' dx='2.4482944151511887' dy='0.7341259770581667' />
<point n='16' x='101.0' y='126.0' dx='2.8654686323038847' dy='0.6944028525022842' />
<point n='17' x='103.0' y='130.0' dx='3.0321317120413207' dy='0.6821832808851894' />
<point n='18' x='106.0' y='150.0' dx='3.28453674808996' dy='0.6210410110648665' />
<point n='19' x='107.0' y='163.0' dx='3.369762186592058' dy='0.5812925083747844' />
<point n='20' x='115.0' y='165.0' dx='4.03400408909932' dy='0.5752271343010863' />
<point n='21' x='126.0' y='181.0' dx='4.949617992037015' dy='0.5263678814333571' />
<point n='22' x='128.0' y='187.0' dx='5.116625416980523' dy='0.5080321794741652' />
<point n='23' x='129.0' y='203.0' dx='5.202367373291723' dy='0.459109481270937' />
<point n='24' x='135.0' y='215.0' dx='5.702356612504032' dy='0.42245076641965296' />
<point n='25' x='149.0' y='248.0' dx='6.869859033681263' dy='0.3216234392447468' />
<point n='26' x='136.0' y='224.0' dx='5.786893360593994' dy='0.3949345244137652' />
<point n='27' x='134.0' y='234.0' dx='5.622640697299041' dy='0.3643411836361792' />
<point n='28' x='137.0' y='243.0' dx='5.8731518347143' dy='0.33683763069739125' />
<point n='29' x='155.0' y='249.0' dx='7.3679543742601945' dy='0.3186034412749975' />
<point n='30' x='161.0' y='257.0' dx='7.867254923060366' dy='0.29417698710790785' />
<point n='31' x='169.0' y='262.0' dx='8.532013343376732' dy='0.27893741752106394' />
<point n='32' x='173.0' y='272.0' dx='8.865683848057675' dy='0.2483821439447771' />
<point n='33' x='184.0' y='277.0' dx='9.779403852361991' dy='0.23316160795858287' />
<point n='34' x='202.0' y='276.0' dx='11.273001183686642' dy='0.23633387473352951' />
<point n='35' x='203.0' y='287.0' dx='11.357882276982671' dy='0.20270150238554474' />
<point n='36' x='208.0' y='310.0' dx='11.776778220165713' dy='0.13239772611917577' />
<point n='37' x='225.0' y='316.0' dx='13.188593565048961' dy='0.11415719216323206' />
<point n='38' x='237.0' y='315.0' dx='14.184267728397717' dy='0.11729139173687964' />
<point n='39' x='242.0' y='325.0' dx='14.60092542774131' dy='0.08674246269414276' />
<point n='40' x='256.0' y='325.0' dx='15.762746153018398' dy='0.08683128616384128' />
<point n='41' x='282.0' y='324.0' dx='17.920241041644243' dy='0.09005430920718727' />
<point n='42' x='306.0' y='325.0' dx='19.912105886150858' dy='0.08714851284133596' />
<point n='43' x='328.0' y='324.0' dx='21.73765199612611' dy='0.09034615775048227' />
</data>
