<?xml version = '1.0'  encoding = 'ISO-8859-1'  standalone = 'yes' ?>
<!-- PlotDigitizer data file: created on Mon Nov 06 00:30:38 EST 2017 -->
<data>
<image file='FOUNT0713_groupB.png' />
<axesnames x='months'  y='p' />
<calibpoints minXaxisX='51.0' minXaxisY='233.0' maxXaxisX='414.5' maxXaxisY='233.0' minYaxisX='49.5' minYaxisY='232.5' maxYaxisX='49.0' maxYaxisY='48.5' aX1='0.0' aX2='36.0' aY1='0.0' aY2='1.0' isXLog='false' isYLog='false' />
<point n='0' x='59.0' y='54.5' dx='0.7922971114167812' dy='0.9673913043478259' />
<point n='1' x='82.0' y='54.5' dx='3.0701513067400272' dy='0.9673913043478259' />
<point n='2' x='82.5' y='60.0' dx='3.1196698762035764' dy='0.9374999999999999' />
<point n='3' x='99.0' y='60.5' dx='4.753782668500688' dy='0.9347826086956521' />
<point n='4' x='98.0' y='66.0' dx='4.65474552957359' dy='0.9048913043478259' />
<point n='5' x='112.5' y='66.0' dx='6.090784044016506' dy='0.9048913043478259' />
<point n='6' x='112.5' y='71.5' dx='6.090784044016506' dy='0.8749999999999999' />
<point n='7' x='134.5' y='71.5' dx='8.269601100412654' dy='0.8749999999999999' />
<point n='8' x='134.0' y='76.5' dx='8.220082530949107' dy='0.8478260869565216' />
<point n='9' x='148.5' y='77.5' dx='9.65612104539202' dy='0.8423913043478259' />
<point n='10' x='155.0' y='94.0' dx='10.299862448418157' dy='0.7527173913043478' />
<point n='11' x='197.5' y='94.0' dx='14.508940852819805' dy='0.7527173913043478' />
<point n='12' x='198.5' y='100.0' dx='14.607977991746903' dy='0.7201086956521738' />
<point n='13' x='289.5' y='101.0' dx='23.62035763411279' dy='0.7146739130434782' />
<point n='14' x='290.0' y='115.5' dx='23.66987620357634' dy='0.6358695652173912' />
<point n='15' x='383.5' y='115.5' dx='32.92984869325997' dy='0.6358695652173912' />
</data>
