<?xml version = '1.0'  encoding = 'ISO-8859-1'  standalone = 'yes' ?>
<!-- PlotDigitizer data file: created on Fri Mar 08 16:50:16 EST 2019 -->
<data>
<image file='OS.png' />
<axesnames x='months'  y='p' />
<calibpoints minXaxisX='352.0' minXaxisY='618.6666666666666' maxXaxisX='1189.3333333333333' maxXaxisY='620.0' minYaxisX='352.0' minYaxisY='618.6666666666666' maxYaxisX='350.6666666666667' maxYaxisY='58.666666666666664' aX1='0.0' aX2='72.0' aY1='0.0' aY2='1.0' isXLog='false' isYLog='false' />
<point n='0' x='358.6666666666667' y='60.0' dx='0.49675317266123287' dy='0.9976417866309776' />
<point n='1' x='368.0' y='69.33333333333333' dx='1.3005768474967354' dy='0.9810015961540649' />
<point n='2' x='396.0' y='70.66666666666667' dx='3.7083966175184138' dy='0.9787002528823661' />
<point n='3' x='422.6666666666667' y='93.33333333333333' dx='6.004488000304274' dy='0.9382997357436145' />
<point n='4' x='442.6666666666667' y='125.33333333333333' dx='7.728610368041384' dy='0.8812135320500912' />
<point n='5' x='472.0' y='164.0' dx='10.25619128516551' dy='0.8122490606955592' />
<point n='6' x='494.6666666666667' y='213.33333333333334' dx='12.211985749965134' dy='0.7242179413783036' />
<point n='7' x='509.3333333333333' y='221.33333333333334' dx='13.474224425371144' dy='0.7099738776686293' />
<point n='8' x='528.0' y='266.6666666666667' dx='15.085523029527' dy='0.629074268555765' />
<point n='9' x='554.6666666666666' y='316.0' dx='17.385265666797668' dy='0.5410545232579741' />
<point n='10' x='568.0' y='317.3333333333333' dx='18.5319421377588' dy='0.5387114752482381' />
<point n='11' x='609.3333333333334' y='370.6666666666667' dx='22.093375762262777' dy='0.4435905504646288' />
<point n='12' x='666.6666666666666' y='428.0' dx='27.03114976482372' dy='0.34137223753502255' />
<point n='13' x='701.3333333333334' y='464.0' dx='30.01696311979413' dy='0.27718485435568097' />
<point n='14' x='737.3333333333334' y='472.0' dx='33.11359204837913' dy='0.26300145208315184' />
<point n='15' x='798.6666666666666' y='502.6666666666667' dx='38.39166296892631' dy='0.20841374133204948' />
<point n='16' x='864.0' y='524.0' dx='44.01240412287487' dy='0.17050413445607537' />
<point n='17' x='906.6666666666666' y='536.0' dx='47.68282769375104' dy='0.14919680465879848' />
<point n='18' x='969.3333333333334' y='536.0' dx='53.071349062464364' dy='0.14937499763041262' />
<point n='19' x='992.0' y='553.3333333333334' dx='55.0227620218822' dy='0.11848695210400395' />
<point n='20' x='1084.0' y='553.3333333333334' dx='62.93356998871661' dy='0.11874855455169286' />
<point n='21' x='1088.0' y='565.3333333333334' dx='63.27916122570588' dy='0.09733127589959012' />
<point n='22' x='1118.6666666666667' y='564.0' dx='65.91591465192643' dy='0.09979943812343861' />
<point n='23' x='1122.6666666666667' y='572.0' dx='66.26095820074296' dy='0.08552504369519154' />
<point n='24' x='1181.3333333333333' y='572.0' dx='71.3055313969852' dy='0.08569186264734108' />
</data>
