<?xml version = '1.0'  encoding = 'ISO-8859-1'  standalone = 'yes' ?>
<!-- PlotDigitizer data file: created on Wed Nov 07 20:59:30 EST 2018 -->
<data>
<image file='null' />
<axesnames x='months'  y='p' />
<calibpoints minXaxisX='140.0' minXaxisY='461.0' maxXaxisX='868.0' maxXaxisY='460.0' minYaxisX='140.0' minYaxisY='461.0' maxYaxisX='140.0' maxYaxisY='41.0' aX1='0.0' aX2='16.0' aY1='0.0' aY2='1.0' isXLog='false' isYLog='false' />
<point n='0' x='139.0' y='41.0' dx='-0.00929837636914188' dy='1.000003270538985' />
<point n='1' x='167.0' y='38.0' dx='0.6061756464805623' dy='1.007054552590267' />
<point n='2' x='169.0' y='53.0' dx='0.6496787644933355' dy='0.9713337257980116' />
<point n='3' x='190.0' y='52.0' dx='1.1112465447135298' dy='0.9736459968602826' />
<point n='4' x='203.0' y='74.0' dx='1.3962961215883478' dy='0.9212225274725275' />
<point n='5' x='209.0' y='108.0' dx='1.5271375604969961' dy='0.8402505232862377' />
<point n='6' x='218.0' y='121.0' dx='1.7245469211392788' dy='0.8092687074829934' />
<point n='7' x='236.0' y='134.0' dx='2.119758106361502' dy='0.7782574568288855' />
<point n='8' x='251.0' y='135.0' dx='2.4493976244610707' dy='0.7758274463631607' />
<point n='9' x='259.0' y='162.0' dx='2.624406351123147' dy='0.7115155677655679' />
<point n='10' x='266.0' y='164.0' dx='2.7781918356179904' dy='0.7067307692307694' />
<point n='11' x='278.0' y='195.0' dx='3.0409917261809296' dy='0.6328819989534276' />
<point n='12' x='288.0' y='208.0' dx='3.260379067332095' dy='0.6018969126111984' />
<point n='13' x='303.0' y='210.0' dx='3.589988395897998' dy='0.5970859497645213' />
<point n='14' x='304.0' y='215.0' dx='3.6118154287385504' dy='0.5851779173207746' />
<point n='15' x='316.0' y='215.0' dx='3.875551194845138' dy='0.5851386708529568' />
<point n='16' x='324.0' y='253.0' dx='4.050227836636887' dy='0.49463631606488767' />
<point n='17' x='347.0' y='253.0' dx='4.555721388341181' dy='0.49456109366823664' />
<point n='18' x='351.0' y='265.0' dx='4.643271035972717' dy='0.46597658294086874' />
<point n='19' x='362.0' y='264.0' dx='4.885059011104089' dy='0.46832155939298814' />
<point n='20' x='363.0' y='273.0' dx='4.9067652858099775' dy='0.4468897174254318' />
<point n='21' x='371.0' y='273.0' dx='5.082589129881037' dy='0.4468635531135533' />
<point n='22' x='373.0' y='280.0' dx='5.126333764163138' dy='0.4301903453689171' />
<point n='23' x='394.0' y='279.0' dx='5.587901544383333' dy='0.43250261643118804' />
<point n='24' x='396.0' y='286.0' dx='5.631646178665435' dy='0.4158294086865517' />
<point n='25' x='410.0' y='287.0' dx='5.939307716256123' dy='0.4134026687598117' />
<point n='26' x='436.0' y='302.0' dx='6.510282366482072' dy='0.3776033490319206' />
<point n='27' x='450.0' y='323.0' dx='6.817340113399438' dy='0.32755756148613313' />
<point n='28' x='476.0' y='349.0' dx='7.387982678755059' dy='0.26556776556776573' />
<point n='29' x='491.0' y='349.0' dx='7.717652386388296' dy='0.26551870748299344' />
<point n='30' x='501.0' y='352.0' dx='7.9373416228761196' dy='0.2583431449502879' />
<point n='31' x='515.0' y='378.0' dx='8.244248422125157' dy='0.19639259549973853' />
<point n='32' x='550.0' y='383.0' dx='9.013326792267708' dy='0.1843733647305078' />
<point n='33' x='552.0' y='396.0' dx='9.056890289347812' dy='0.15341444270015714' />
<point n='34' x='556.0' y='432.0' dx='9.143715388171366' dy='0.0676870748299323' />
<point n='35' x='705.0' y='432.0' dx='12.418434483994833' dy='0.06719976452119347' />
<point n='36' x='707.0' y='441.0' dx='12.462118739209604' dy='0.045764652014652185' />
<point n='37' x='759.0' y='442.0' dx='13.604943536137817' dy='0.043213631606489056' />
</data>
