<?xml version = '1.0'  encoding = 'ISO-8859-1'  standalone = 'yes' ?>
<!-- PlotDigitizer data file: created on Fri Nov 16 16:11:18 EST 2018 -->
<data>
<image file='null' />
<axesnames x='days'  y='p' />
<calibpoints minXaxisX='50.0' minXaxisY='295.0' maxXaxisX='348.0' maxXaxisY='289.0' minYaxisX='50.0' minYaxisY='295.0' maxYaxisX='51.0' maxYaxisY='36.0' aX1='0.0' aX2='400.0' aY1='0.0' aY2='1.0' isXLog='false' isYLog='false' />
<point n='0' x='55.0' y='37.0' dx='13.678523187753257' dy='0.9958277184616979' />
<point n='1' x='71.0' y='37.0' dx='35.14633048176496' dy='0.9945838084378563' />
<point n='2' x='73.0' y='63.0' dx='37.127420081044576' dy='0.8940344148439929' />
<point n='3' x='80.0' y='63.0' dx='46.51958577217469' dy='0.8934902042085623' />
<point n='4' x='85.0' y='102.0' dx='52.17469608284557' dy='0.742510625064787' />
<point n='5' x='87.0' y='142.0' dx='53.77757766771725' dy='0.5879029750181404' />
<point n='6' x='91.0' y='158.0' dx='58.71229176046826' dy='0.5258111329947133' />
<point n='7' x='94.0' y='171.0' dx='62.38631247185954' dy='0.4753809474448014' />
<point n='8' x='97.0' y='183.0' dx='66.08734804142277' dy='0.4288120659272312' />
<point n='9' x='104.0' y='185.0' dx='75.42548401620893' dy='0.4205452472271173' />
<point n='10' x='105.0' y='197.0' dx='76.4430436740207' dy='0.37413185446252717' />
<point n='11' x='113.0' y='197.0' dx='87.17694732102656' dy='0.3735098994506064' />
<point n='12' x='118.0' y='226.0' dx='93.10220621341738' dy='0.2611433606302477' />
<point n='13' x='120.0' y='251.0' dx='95.11031067086897' dy='0.16445527106872593' />
<point n='14' x='177.0' y='252.0' dx='171.56235929761368' dy='0.1561625375764486' />
<point n='15' x='177.0' y='271.0' dx='171.04907699234576' dy='0.08279776096195723' />
<point n='16' x='184.0' y='273.0' dx='180.38721296713192' dy='0.0745309422618432' />
<point n='17' x='182.0' y='291.0' dx='177.21746960828455' dy='0.005182958432673468' />
</data>
