<?xml version = '1.0'  encoding = 'ISO-8859-1'  standalone = 'yes' ?>
<!-- PlotDigitizer data file: created on Fri Feb 22 18:25:59 IST 2019 -->
<data>
<image file='226.PNG' />
<axesnames x='Weeks'  y='PFS' />
<calibpoints minXaxisX='73.0' minXaxisY='331.0' maxXaxisX='528.0' maxXaxisY='331.0' minYaxisX='73.0' minYaxisY='331.0' maxYaxisX='71.0' maxYaxisY='11.0' aX1='0.0' aX2='100.0' aY1='0.0' aY2='1.0' isXLog='false' isYLog='false' />
<point n='0' x='72.0' y='14.0' dx='-0.219780219780219' dy='0.9906250000000001' />
<point n='1' x='72.0' y='14.0' dx='-0.219780219780219' dy='0.9906250000000001' />
<point n='2' x='78.0' y='18.0' dx='1.0989010989010985' dy='0.978125' />
<point n='3' x='78.0' y='18.0' dx='1.0989010989010985' dy='0.978125' />
<point n='4' x='89.0' y='21.0' dx='3.5164835164835146' dy='0.96875' />
<point n='5' x='89.0' y='21.0' dx='3.5164835164835146' dy='0.96875' />
<point n='6' x='95.0' y='30.0' dx='4.835164835164836' dy='0.940625' />
<point n='7' x='92.0' y='29.0' dx='4.175824175824175' dy='0.9437500000000001' />
<point n='8' x='97.0' y='39.0' dx='5.274725274725274' dy='0.9125000000000001' />
<point n='9' x='97.0' y='39.0' dx='5.274725274725274' dy='0.9125000000000001' />
<point n='10' x='96.0' y='53.0' dx='5.054945054945055' dy='0.86875' />
<point n='11' x='96.0' y='53.0' dx='5.054945054945055' dy='0.86875' />
<point n='12' x='100.0' y='68.0' dx='5.934065934065934' dy='0.821875' />
<point n='13' x='100.0' y='68.0' dx='5.934065934065934' dy='0.821875' />
<point n='14' x='99.0' y='81.0' dx='5.714285714285715' dy='0.78125' />
<point n='15' x='99.0' y='81.0' dx='5.714285714285715' dy='0.78125' />
<point n='16' x='101.0' y='91.0' dx='6.153846153846153' dy='0.75' />
<point n='17' x='101.0' y='91.0' dx='6.153846153846153' dy='0.75' />
<point n='18' x='100.0' y='107.0' dx='5.934065934065934' dy='0.7' />
<point n='19' x='100.0' y='107.0' dx='5.934065934065934' dy='0.7' />
<point n='20' x='103.0' y='124.0' dx='6.593406593406595' dy='0.6468750000000001' />
<point n='21' x='106.0' y='138.0' dx='7.252747252747252' dy='0.603125' />
<point n='22' x='107.0' y='168.0' dx='7.472527472527471' dy='0.509375' />
<point n='23' x='107.0' y='168.0' dx='7.472527472527471' dy='0.509375' />
<point n='24' x='108.0' y='184.0' dx='7.692307692307693' dy='0.459375' />
<point n='25' x='108.0' y='184.0' dx='7.692307692307693' dy='0.459375' />
<point n='26' x='115.0' y='190.0' dx='9.23076923076923' dy='0.44062500000000004' />
<point n='27' x='115.0' y='190.0' dx='9.23076923076923' dy='0.44062500000000004' />
<point n='28' x='115.0' y='199.0' dx='9.23076923076923' dy='0.4125' />
<point n='29' x='127.0' y='204.0' dx='11.868131868131869' dy='0.396875' />
<point n='30' x='127.0' y='204.0' dx='11.868131868131869' dy='0.396875' />
<point n='31' x='128.0' y='209.0' dx='12.087912087912088' dy='0.38125' />
<point n='32' x='128.0' y='209.0' dx='12.087912087912088' dy='0.38125' />
<point n='33' x='134.0' y='217.0' dx='13.406593406593405' dy='0.35624999999999996' />
<point n='34' x='134.0' y='217.0' dx='13.406593406593405' dy='0.35624999999999996' />
<point n='35' x='134.0' y='226.0' dx='13.406593406593405' dy='0.328125' />
<point n='36' x='150.0' y='228.0' dx='16.92307692307692' dy='0.321875' />
<point n='37' x='163.0' y='224.0' dx='19.78021978021978' dy='0.334375' />
<point n='38' x='165.0' y='245.0' dx='20.21978021978022' dy='0.26875000000000004' />
<point n='39' x='188.0' y='251.0' dx='25.274725274725277' dy='0.25' />
<point n='40' x='188.0' y='251.0' dx='25.274725274725277' dy='0.25' />
<point n='41' x='211.0' y='253.0' dx='30.32967032967033' dy='0.24375000000000002' />
<point n='42' x='211.0' y='253.0' dx='30.32967032967033' dy='0.24375000000000002' />
<point n='43' x='219.0' y='266.0' dx='32.08791208791209' dy='0.203125' />
<point n='44' x='225.0' y='276.0' dx='33.40659340659341' dy='0.171875' />
<point n='45' x='225.0' y='276.0' dx='33.40659340659341' dy='0.171875' />
<point n='46' x='236.0' y='277.0' dx='35.824175824175825' dy='0.16874999999999996' />
<point n='47' x='240.0' y='287.0' dx='36.7032967032967' dy='0.13749999999999996' />
<point n='48' x='240.0' y='287.0' dx='36.7032967032967' dy='0.13749999999999996' />
<point n='49' x='251.0' y='287.0' dx='39.12087912087912' dy='0.13749999999999996' />
<point n='50' x='251.0' y='287.0' dx='39.12087912087912' dy='0.13749999999999996' />
<point n='51' x='261.0' y='305.0' dx='41.31868131868132' dy='0.08125000000000004' />
<point n='52' x='261.0' y='305.0' dx='41.31868131868132' dy='0.08125000000000004' />
<point n='53' x='264.0' y='318.0' dx='41.97802197802198' dy='0.04062500000000002' />
<point n='54' x='264.0' y='317.0' dx='41.97802197802198' dy='0.043749999999999956' />
<point n='55' x='283.0' y='313.0' dx='46.15384615384615' dy='0.05625000000000002' />
<point n='56' x='317.0' y='316.0' dx='53.62637362637362' dy='0.046875' />
<point n='57' x='334.0' y='316.0' dx='57.36263736263736' dy='0.046875' />
<point n='58' x='334.0' y='316.0' dx='57.36263736263736' dy='0.046875' />
<point n='59' x='367.0' y='314.0' dx='64.61538461538461' dy='0.05312499999999998' />
<point n='60' x='367.0' y='314.0' dx='64.61538461538461' dy='0.05312499999999998' />
<point n='61' x='388.0' y='314.0' dx='69.23076923076923' dy='0.05312499999999998' />
<point n='62' x='388.0' y='314.0' dx='69.23076923076923' dy='0.05312499999999998' />
<point n='63' x='403.0' y='315.0' dx='72.52747252747253' dy='0.050000000000000044' />
<point n='64' x='406.0' y='333.0' dx='73.18681318681318' dy='-0.006250000000000089' />
<point n='65' x='406.0' y='333.0' dx='73.18681318681318' dy='-0.006250000000000089' />
</data>
