<?xml version = '1.0'  encoding = 'ISO-8859-1'  standalone = 'yes' ?>
<!-- PlotDigitizer data file: created on Fri Feb 22 21:12:05 IST 2019 -->
<data>
<image file='309.PNG' />
<axesnames x='Months'  y='PFS (Probability)' />
<calibpoints minXaxisX='65.0' minXaxisY='336.0' maxXaxisX='795.0' maxXaxisY='338.0' minYaxisX='65.0' minYaxisY='336.0' maxYaxisX='65.0' maxYaxisY='10.0' aX1='0.0' aX2='45.0' aY1='0.0' aY2='1.0' isXLog='false' isYLog='false' />
<point n='0' x='67.0' y='11.0' dx='0.06839881104288992' dy='0.9969493234725606' />
<point n='1' x='73.0' y='16.0' dx='0.4391034783000318' dy='0.9816623245650894' />
<point n='2' x='82.0' y='16.0' dx='0.9938938345368022' dy='0.9817379611732078' />
<point n='3' x='90.0' y='17.0' dx='1.4872097038115681' dy='0.9787377090511807' />
<point n='4' x='93.0' y='24.0' dx='1.6733220242295053' dy='0.95729052861585' />
<point n='5' x='93.0' y='24.0' dx='1.6733220242295053' dy='0.95729052861585' />
<point n='6' x='96.0' y='33.0' dx='1.8597721165538266' dy='0.929708378855366' />
<point n='7' x='96.0' y='33.0' dx='1.8597721165538266' dy='0.929708378855366' />
<point n='8' x='99.0' y='39.0' dx='2.04571555101857' dy='0.911328683082612' />
<point n='9' x='99.0' y='39.0' dx='2.04571555101857' dy='0.911328683082612' />
<point n='10' x='109.0' y='42.0' dx='2.662655938030115' dy='0.902210269770569' />
<point n='11' x='113.0' y='42.0' dx='2.9092294296909014' dy='0.9022438860408437' />
<point n='12' x='114.0' y='47.0' dx='2.9717172323720593' dy='0.886914866795529' />
<point n='13' x='118.0' y='48.0' dx='3.2184596099860387' dy='0.8838809984032271' />
<point n='14' x='123.0' y='56.0' dx='3.528027562187561' dy='0.8593831414404571' />
<point n='15' x='123.0' y='56.0' dx='3.528027562187561' dy='0.8593831414404571' />
<point n='16' x='124.0' y='68.0' dx='3.5916975665410655' dy='0.8225817295571056' />
<point n='17' x='125.0' y='68.0' dx='3.653340939456262' dy='0.8225901336246743' />
<point n='18' x='130.0' y='71.0' dx='3.9620644618918233' dy='0.8134296999747876' />
<point n='19' x='130.0' y='71.0' dx='3.9620644618918233' dy='0.8134296999747876' />
<point n='20' x='134.0' y='80.0' dx='4.21015792713134' dy='0.7858559542818724' />
<point n='21' x='134.0' y='81.0' dx='4.210326813084532' dy='0.7827884696192957' />
<point n='22' x='137.0' y='94.0' dx='4.397452449221622' dy='0.7429363812085048' />
<point n='23' x='137.0' y='94.0' dx='4.397452449221622' dy='0.7429363812085048' />
<point n='24' x='144.0' y='92.0' dx='4.828618287721615' dy='0.7491301790066391' />
<point n='25' x='153.0' y='98.0' dx='5.38442195967754' dy='0.7308009076392974' />
<point n='26' x='154.0' y='114.0' dx='5.448767507843814' dy='0.6817295571056391' />
<point n='27' x='156.0' y='129.0' dx='5.574587542972092' dy='0.6357340953021262' />
<point n='28' x='158.0' y='138.0' dx='5.699394262381216' dy='0.6081435414740733' />
<point n='29' x='167.0' y='144.0' dx='6.255197934337141' dy='0.5898142701067315' />
<point n='30' x='175.0' y='146.0' dx='6.7486826895651' dy='0.5837465333221279' />
<point n='31' x='175.0' y='146.0' dx='6.7486826895651' dy='0.5837465333221279' />
<point n='32' x='177.0' y='158.0' dx='6.873996066833802' dy='0.5469535255063449' />
<point n='33' x='183.0' y='171.0' dx='7.246051821716482' dy='0.5071266492982602' />
<point n='34' x='188.0' y='182.0' dx='7.556126431777579' dy='0.47342633834776016' />
<point n='35' x='197.0' y='191.0' dx='8.11243676159308' dy='0.4458946129926883' />
<point n='36' x='211.0' y='204.0' dx='8.977639499797334' dy='0.40613496932515325' />
<point n='37' x='211.0' y='204.0' dx='8.977639499797334' dy='0.40613496932515325' />
<point n='38' x='236.0' y='218.0' dx='10.521088226021945' dy='0.3634002857382972' />
<point n='39' x='236.0' y='218.0' dx='10.521088226021945' dy='0.3634002857382972' />
<point n='40' x='243.0' y='221.0' dx='10.9530984942879' dy='0.3542566602235482' />
<point n='41' x='244.0' y='221.0' dx='11.014741867203096' dy='0.3542650642911168' />
<point n='42' x='253.0' y='223.0' dx='11.569869995346252' dy='0.34820573157408174' />
<point n='43' x='253.0' y='223.0' dx='11.569869995346252' dy='0.34820573157408174' />
<point n='44' x='260.0' y='227.0' dx='12.002049149565398' dy='0.33599462139675584' />
<point n='45' x='260.0' y='227.0' dx='12.002049149565398' dy='0.33599462139675584' />
<point n='46' x='264.0' y='232.0' dx='12.24946707099215' dy='0.32069081435414726' />
<point n='47' x='264.0' y='232.0' dx='12.24946707099215' dy='0.32069081435414726' />
<point n='48' x='275.0' y='238.0' dx='12.928557488778466' dy='0.302378351121943' />
<point n='49' x='275.0' y='238.0' dx='12.928557488778466' dy='0.302378351121943' />
<point n='50' x='282.0' y='243.0' dx='13.360905528950802' dy='0.2870997562820403' />
<point n='51' x='326.0' y='245.0' dx='16.073551709125844' dy='0.2813345659299099' />
<point n='52' x='355.0' y='240.0' dx='17.860365093900587' dy='0.2969157072022858' />
<point n='53' x='360.0' y='253.0' dx='18.17077747586807' dy='0.25708042692663235' />
<point n='54' x='360.0' y='253.0' dx='18.17077747586807' dy='0.25708042692663235' />
<point n='55' x='373.0' y='266.0' dx='18.974336841157125' dy='0.21731237919152868' />
<point n='56' x='393.0' y='267.0' dx='20.207373185414255' dy='0.21441297588032582' />
<point n='57' x='393.0' y='267.0' dx='20.207373185414255' dy='0.21441297588032582' />
<point n='58' x='408.0' y='267.0' dx='21.132023779142205' dy='0.21453903689385645' />
<point n='59' x='414.0' y='277.0' dx='21.50357287616531' dy='0.1839146146735019' />
<point n='60' x='436.0' y='289.0' dx='22.861753711737947' dy='0.14728968820909305' />
<point n='61' x='544.0' y='304.0' dx='29.52177127587708' dy='0.10218505756786267' />
<point n='62' x='481.0' y='289.0' dx='25.635705492921797' dy='0.14766787124968472' />
<point n='63' x='515.0' y='286.0' dx='27.731073514178913' dy='0.15715606353475076' />
<point n='64' x='515.0' y='286.0' dx='27.731073514178913' dy='0.15715606353475076' />
<point n='65' x='543.0' y='290.0' dx='29.457763499617187' dy='0.14512143877636774' />
<point n='66' x='543.0' y='290.0' dx='29.457763499617187' dy='0.14512143877636774' />
<point n='67' x='545.0' y='304.0' dx='29.58341464879227' dy='0.1021934616354313' />
<point n='68' x='589.0' y='306.0' dx='32.29606082896732' dy='0.096428271283301' />
<point n='69' x='631.0' y='305.0' dx='34.88491360545238' dy='0.09984872678376333' />
<point n='70' x='691.0' y='306.0' dx='38.583684866317384' dy='0.09728548617530874' />
<point n='71' x='753.0' y='306.0' dx='42.40557398705958' dy='0.09780653836456832' />
<point n='72' x='753.0' y='306.0' dx='42.40557398705958' dy='0.09780653836456832' />
<point n='73' x='771.0' y='306.0' dx='43.51515469953312' dy='0.09795781158080497' />
<point n='74' x='771.0' y='306.0' dx='43.51515469953312' dy='0.09795781158080497' />
</data>
